django_management_commands_logging/__init__.py
django_management_commands_logging/core.py
django_mc_logging-0.0.5.dist-info/LICENSE
django_mc_logging-0.0.5.dist-info/METADATA
django_mc_logging-0.0.5.dist-info/WHEEL
django_mc_logging-0.0.5.dist-info/top_level.txt
django_mc_logging-0.0.5.dist-info/RECORD
