Metadata-Version: 2.1
Name: django-mc-logging
Version: 0.0.5
Summary: Django utility for modular logging for management commands.
Author: Walter Gams
Author-email: Bruno Miranda <brunofelippemm@gmail.com>, Paulo Viana <pvictor_vs@hotmail.com>
Project-URL: Homepage, https://github.com/brunofelippemm/django_management_commands_logging
Project-URL: Bug Tracker, https://github.com/brunofelippemm/django_management_commands_logging/issues
Classifier: Development Status :: 3 - Alpha
Classifier: License :: OSI Approved :: MIT License
Classifier: Operating System :: OS Independent
Classifier: Programming Language :: Python :: 3
Requires-Python: >=3.7
License-File: LICENSE
Requires-Dist: Django (>=3.1.5)
